hboptimize/__init__.py
hboptimize/api.py
hboptimize/config.py
hboptimize/exceptions.py
hboptimize/types.py
hboptimize/core/acquisition.py
hboptimize/core/optimizer.py
hboptimize/core/scheduler.py
hboptimize/core/search_space.py
hboptimize/core/surrogate.py
hboptimize/risk/base.py
hboptimize/risk/cv.py
hboptimize/runners/sklearn_adapter.py
hboptimize/utils/seeding.py
hboptimize/utils/storage.py
hboptimize-0.1.0.dist-info/licenses/LICENSE
hboptimize-0.1.0.dist-info/METADATA
hboptimize-0.1.0.dist-info/WHEEL
hboptimize-0.1.0.dist-info/top_level.txt
hboptimize-0.1.0.dist-info/RECORD
