Metadata-Version: 2.4
Name: hboptimize
Version: 0.1.0
Summary: Bias-Variance Aware Bayesian Optimization for Hyperparameter Tuning
Author: Dashiell Decker
License: MIT
Project-URL: Homepage, https://github.com/DashDecker/HBOptimize
Project-URL: Documentation, https://hboptimize.readthedocs.io
Project-URL: Repository, https://github.com/DashDecker/HBOptimize
Project-URL: Bug Tracker, https://github.com/DashDecker/HBOptimize/issues
Keywords: bayesian-optimization,hyperparameter-tuning,machine-learning,bias-variance,cross-validation
Classifier: Development Status :: 3 - Alpha
Classifier: Intended Audience :: Science/Research
Classifier: Intended Audience :: Developers
Classifier: Topic :: Scientific/Engineering :: Artificial Intelligence
Classifier: Topic :: Software Development :: Libraries :: Python Modules
Classifier: License :: OSI Approved :: MIT License
Classifier: Programming Language :: Python :: 3
Classifier: Programming Language :: Python :: 3.9
Classifier: Programming Language :: Python :: 3.10
Classifier: Programming Language :: Python :: 3.11
Classifier: Programming Language :: Python :: 3.12
Classifier: Programming Language :: Python :: 3.13
Requires-Python: >=3.9
License-File: LICENSE
Requires-Dist: numpy>=1.20.0
Requires-Dist: scipy>=1.7.0
Requires-Dist: scikit-learn>=1.0.0
Requires-Dist: pydantic>=2.0.0
Provides-Extra: dev
Requires-Dist: pytest>=7.0.0; extra == "dev"
Requires-Dist: pytest-cov>=4.0.0; extra == "dev"
Requires-Dist: black>=22.0.0; extra == "dev"
Requires-Dist: mypy>=1.0.0; extra == "dev"
Requires-Dist: ruff>=0.1.0; extra == "dev"
Provides-Extra: viz
Requires-Dist: matplotlib>=3.5.0; extra == "viz"
Dynamic: license-file
